MyJpHolidays/MyJpHolidays.py
MyJpHolidays/__init__.py
MyJpHolidays-0.8.5.dist-info/LICENSE
MyJpHolidays-0.8.5.dist-info/METADATA
MyJpHolidays-0.8.5.dist-info/WHEEL
MyJpHolidays-0.8.5.dist-info/top_level.txt
MyJpHolidays-0.8.5.dist-info/RECORD
