Metadata-Version: 2.1
Name: MyJpHolidays
Version: 0.8.5
Summary: MyJpHolidays: You get a combined list of Japan-Holidays. You can customize orignal holidays used ini-file.
Home-page: https://github.com/Supper-Smille/MyJpHolidays20230412
Author: Supper-Smille
Author-email: ak2004@support.email.ne.jp
Maintainer: Supper-Smille
Maintainer-email: ak2004@support.email.ne.jp
License: MIT License
Download-URL: https://github.com/Supper-Smille/MyJpHolidays20230412
Platform: UNKNOWN
Classifier: Development Status :: 4 - Beta
Classifier: Environment :: Console
Classifier: Environment :: Win32 (MS Windows)
Classifier: Intended Audience :: End Users/Desktop
Classifier: Intended Audience :: Developers
Classifier: Intended Audience :: System Administrators
Classifier: License :: OSI Approved :: MIT License
Classifier: Operating System :: Microsoft :: Windows
Classifier: Programming Language :: Python
Classifier: Topic :: Office/Business
Classifier: Topic :: Office/Business :: Scheduling
Classifier: Topic :: Software Development :: Libraries
Requires-Python: >=3.8.10
Requires-Dist: numpy (>=1.23.1)
